Workbook

Sheet Recap 2026
E1: Peak Leads Group - 2026
B2: Leads | C2: RAW Appt | D2: Appt Issued | E2: Demo | F2: Sale # | G2: Sale $ | H2: Advertsing $ | I2: Advertsing % | J2: Lead to RAW Appt | K2: Appointment Issue Rate | L2: Demo Rate | M2: Sold to Appt Issued | N2: NLIS
A3: January | B3: 9 | C3: 2 | D3: 2 | E3: 2 | F3: 0 | G3: 0 | H3: 1100 | I3: =H3/G3 -> #DIV/0! | J3: =C3/B3 -> 0.22222222 | K3: =D3/B3 -> 0.22222222 | L3: =E3/D3 -> 1 | M3: =F3/D3 -> 0 | N3: =G3/D3 -> 0
A4: February | B4: 82 | C4: 38 | D4: 19 | E4: 15 | F4: 1 | G4: 22000 | H4: 9020 | I4: =H4/G4 -> 0.41 | J4: =C4/B4 -> 0.46341463 | K4: =D4/B4 -> 0.23170732 | L4: =E4/D4 -> 0.78947368 | M4: =F4/D4 -> 0.052631579 | N4: =G4/D4 -> 1157.8947
A5: March | I5: =H5/G5 -> #DIV/0! | J5: =C5/B5 -> #DIV/0! | K5: =D5/B5 -> #DIV/0! | L5: =E5/D5 -> #DIV/0! | M5: =F5/D5 -> #DIV/0! | N5: =G5/D5 -> #DIV/0!
A6: April | I6: =H6/G6 -> #DIV/0! | J6: =C6/B6 -> #DIV/0! | K6: =D6/B6 -> #DIV/0! | L6: =E6/D6 -> #DIV/0! | M6: =F6/D6 -> #DIV/0! | N6: =G6/D6 -> #DIV/0!
A7: May | I7: =H7/G7 -> #DIV/0! | J7: =C7/B7 -> #DIV/0! | K7: =D7/B7 -> #DIV/0! | L7: =E7/D7 -> #DIV/0! | M7: =F7/D7 -> #DIV/0! | N7: =G7/D7 -> #DIV/0!
A8: June | I8: =H8/G8 -> #DIV/0! | J8: =C8/B8 -> #DIV/0! | K8: =D8/B8 -> #DIV/0! | L8: =E8/D8 -> #DIV/0! | M8: =F8/D8 -> #DIV/0! | N8: =G8/D8 -> #DIV/0!
A9: July | I9: =H9/G9 -> #DIV/0! | J9: =C9/B9 -> #DIV/0! | K9: =D9/B9 -> #DIV/0! | L9: =E9/D9 -> #DIV/0! | M9: =F9/D9 -> #DIV/0! | N9: =G9/D9 -> #DIV/0!
A10: August | I10: =H10/G10 -> #DIV/0! | J10: =C10/B10 -> #DIV/0! | K10: =D10/B10 -> #DIV/0! | L10: =E10/D10 -> #DIV/0! | M10: =F10/D10 -> #DIV/0! | N10: =G10/D10 -> #DIV/0!
A11: September | I11: =H11/G11 -> #DIV/0! | J11: =C11/B11 -> #DIV/0! | K11: =D11/B11 -> #DIV/0! | L11: =E11/D11 -> #DIV/0! | M11: =F11/D11 -> #DIV/0! | N11: =G11/D11 -> #DIV/0!
A12: October | I12: =H12/G12 -> #DIV/0! | J12: =C12/B12 -> #DIV/0! | K12: =D12/B12 -> #DIV/0! | L12: =E12/D12 -> #DIV/0! | M12: =F12/D12 -> #DIV/0! | N12: =G12/D12 -> #DIV/0!
A13: November | I13: =H13/G13 -> #DIV/0! | J13: =C13/B13 -> #DIV/0! | K13: =D13/B13 -> #DIV/0! | L13: =E13/D13 -> #DIV/0! | M13: =F13/D13 -> #DIV/0! | N13: =G13/D13 -> #DIV/0!
A14: December | I14: =H14/'Recap 2024'!G14 -> #REF! | J14: ='Recap 2024'!C14/'Recap 2024'!B14 -> #REF! | K14: ='Recap 2024'!D14/'Recap 2024'!B14 -> #REF! | L14: ='Recap 2024'!E14/'Recap 2024'!D14 -> #REF! | M14: ='Recap 2024'!F14/'Recap 2024'!D14 -> #REF! | N14: ='Recap 2024'!G14/'Recap 2024'!D14 -> #REF!
A16: Totals | B16: =SUM(B3:B14) -> 91 | C16: =SUM(C3:C14) -> 40 | D16: =SUM(D3:D14) -> 21 | E16: =SUM(E3:E14) -> 17 | F16: =SUM(F3:F14) -> 1 | G16: =SUM(G3:G14) -> 22000 | H16: =SUM(H3:H14) -> 10120 | I16: =H16/G16 -> 0.46 | J16: =C16/B16 -> 0.43956044 | K16: =D16/B16 -> 0.23076923 | L16: =E16/D16 -> 0.80952381 | M16: =F16/D16 -> 0.047619048 | N16: =G16/D16 -> 1047.619
C17: =C16/B16 -> 0.43956044 | D17: =D16/C16 -> 0.525 | E17: =E16/D16 -> 0.80952381 | F17: =F16/D16 -> 0.047619048
A18: Cost per | B18: =$H$16/B16 -> 111.20879 | C18: =$H$16/C16 -> 253 | D18: =$H$16/D16 -> 481.90476 | E18: =$H$16/E16 -> 595.29412 | F18: =$H$16/F16 -> 10120
G20: =G16/F16 -> 22000
A21: Lead to RAW Appt | B21: =C16/B16 -> 0.43956044
A22: RAW to Issued | B22: =D16/C16 -> 0.525
A23: Issued to Demo | B23: =E16/D16 -> 0.80952381
A24: Demo to Sale | B24: =F16/E16 -> 0.058823529
A25: NSLI | B25: =G16/D16 -> 1047.619
A26: Advertising % | B26: =H16/G16 -> 0.46

Sheet Sales - 
A1: Franchise | B1: lead source | C1: Contact Name | D1: Landed Date | E1: Landed Amount | F1: Sales Person | G1: Status
B2: Peak Leads Group | C2: Ramesh Singh | D2: 46065 | E2: 22000 | F2: Tom Seesz
A9: Totals | E9: =SUM(E1:E8) -> 22000
A11: Less Cancels | E11: =-E4 -> 0
A13: Net Revenue | E13: =E9+E11 -> 22000

Sheet Leads Recap
A1: Name | B1: Pri Phone | C1: Category
A2: May Ly | B2: (612) 443-3866 | C2: 1. LEAD - NEW
A3: Christine Kusensela | B3: (651) 428-0927 | C3: 1. LEAD - NEW
A4: Naomi Gonzalez | B4: (651) 332-0567 | C4: 1. LEAD - NEW
A5: Gloria Nakanwagi | B5: (651) 800-6244 | C5: 2. APPOINTMENT
A6: Latisha Austin | B6: (763) 352-2477 | C6: 2. APPOINTMENT
A7: George {last_name} | B7: (612) 239-9656 | C7: 1. LEAD - NEW
A8: Elizabeth & Frank Hill | B8: (952) 381-1081 | C8: 2. APPOINTMENT
A9: Fatu Ballah | B9: (612) 601-4010 | C9: 1. LEAD - NEW
A10: Hawa Jama | B10: (612) 400-2494 | C10: 2. APPOINTMENT
A11: Sarah Spencer | B11: (651) 675-6834 | C11: 1. LEAD - NEW
A12: Joor Erin | B12: (651) 983-2388 | C12: 2. APPOINTMENT
... A99: Randy & Jill Duevel | B99: (612) 965-4814 | C99: 3. Proposal

Sheet Appt Recap
A1: Id | B1: Name | C1: Pri Phone | D1: Alt Phone | E1: Email | F1: Company | G1: Category | H1: Channel | I1: Lead Date | J1: Appt Date | K1: Sales Rep | L1: Rating | M1: Quote | N1: Notes
A5: 13620414 | B5: Lam Nguyen | G5: 2. APPOINTMENT | H5: Peak Leads Group | J5: 46073 | K5: Tom Seesz | L5: 2 | M5: 34264 | N5: he wanted us to do our system on all the walls in his bathroom. He said he saw a video online and told me that our product looked nothing like what the video was. It wasn't shiny enough. He wanted a whole bathroom remodel told me the price was too too high. He was willing to do it for 15,000.
A6: 13619121 | B6: Abdul Osumanu | G6: 2. APPOINTMENT | H6: Peak Leads Group | J6: 46072 | K6: Ostin Tuma | L6: 2 | N6: Had people installing windows when I got there. Spoke about budget and that's all he wanted. He doesn't want 2 loans, wants to pay off windows before he does the bathroom project.
A7: 13619087 | B7: Abdulla & Kristina Reed | G7: 2. APPOINTMENT | H7: Peak Leads Group | J7: 46072
A8: 13564557 | B8: Alpha Sowe | G8: 2. APPOINTMENT | H8: Peak Leads Group | J8: 46072 | K8: Mike Smeed | L8: 2 | N8: Alpha was sleeping when I arrived.. Wife was not present and he didn't have a plan on what he wanted..
A9: 13616879 | B9: Austin Mueller | G9: 2. APPOINTMENT | H9: Peak Leads Group | J9: 46072
A10: 13615411 | B10: Dave Thompson | G10: 2. APPOINTMENT | H10: Peak Leads Group | J10: 46072 | K10: Mike Smeed | L10: 7 | M10: 18445 | N10: Wife was not present and she will have a say in decision | O10: Wife was not present and she will have a say in decision
A11: 13564541 | B11: Dorothy Evans | G11: 2. APPOINTMENT | H11: Peak Leads Group | J11: 46072
A12: 13643854 | B12: Esther Barrera | G12: 2. APPOINTMENT | H12: Peak Leads Group | J12: 46072
A13: 13619568 | B13: Kenyada Beasley | G13: 2. APPOINTMENT | H13: Peak Leads Group | J13: 46072
A14: 13566373 | B14: Marcus Blamoh | G14: 2. APPOINTMENT | H14: Peak Leads Group | J14: 46072 | K14: Jeff Counter | L14: 10 | M14: 17005 | N14: Bank reject. No options available. SALE BANK REJECT.
A15: 13643748 | B15: Thomas Paye | G15: 2. APPOINTMENT | H15: Peak Leads Group | J15: 46072
A16: 13636139 | B16: Tony Stokes | G16: 2. APPOINTMENT | H16: Peak Leads Group | J16: 46072 | K16: Tori Wilburn | L16: 5 | M16: 35230 | N16: One leg with Tony. Super cool guy. Not sure why he had me there because he’s a GC and has guys that can do the entire bath for the cost of our massive custom Onyx WIS lol. Came in at 35,350. I asked him straight up if he would drop a cool 35gs on a WIS when he and his people can do it for a fraction and he said yes because it would be the showstopper of the bathroom. He told me in the first ten mins he already picked up allll the tile for this project for $1,800 and I told him I’d be happy to shower him what we can do and he was interested in seeing Onyx. 72x48 with a pony wall and custom glass. Said he’s gonna talk to wifey tonight and lmk tomorrow. He gut and remodeled the entire house and it’s honestly beautiful so I’m just confused why he’s thinking about subbing it out to us but I’ll happily hook Mr. Tony up with a showstopping shower
A17: 13614005 | B17: Ebenezer Otu | G17: 2. APPOINTMENT | H17: Peak Leads Group | J17: 46071 | K17: Chris Cornolo | L17: 1 | N17: D - 2 commercial bathrooms in a church. Needs partitions, urinals, and tile work. Partially confused why this appointment was set.
A18: 13548255 | B18: Mariah Glago | G18: 2. APPOINTMENT | H18: Peak Leads Group | J18: 46071
A19: 13564593 | B19: Selam & Todd Ungers | G19: 2. APPOINTMENT | H19: Peak Leads Group | J19: 46071
A20: 13602568 | B20: Jean Rehbein | G20: 2. APPOINTMENT | H20: Peak Leads Group | J20: 46070 | K20: Ostin Tuma
A21: 13458063 | B21: Bedassa & Iftu Tadesse | G21: 2. APPOINTMENT | H21: Peak Leads Group | J21: 46058 | K21: Chris Cornolo | L21: 5 | M21: 17248 | N21: Met with Mr. Only. Wife was a doctor. Home was built in 2020. Interested in replacing master shower. No issues. Just builder grade/fiberglass. Going to chat with wife and get back to me
A22: 13506475 | B22: Mike & Anna Mohn | G22: 2. APPOINTMENT | H22: Peak Leads Group | J22: 46069 | K22: Jeff Counter | L22: 8 | M22: 13820 | N22: Has 2 others coming in behind me. Price was ok. Mr put in a tub himself and cut sheetrock around surround 2' past enclosure. wants to get done.
A23: 13506837 | B23: Peter Vang | G23: 2. APPOINTMENT | H23: Peak Leads Group | J23: 46069 | K23: Tom Seesz | L23: 7 | M23: 15611 | N23: Rental unit possibly 2 to 3 bathrooms. Thought it was a lot of money said he needs time to think about it and get other beds. We'll make a decision in a week follow up February
A24: 13542010 | B24: Abdimahad Santur & Ladan Nur | G24: 2. APPOINTMENT | H24: Peak Leads Group | J24: 46066 | K24: Mike Smeed | L24: 6 | M24: 29202 | N24: Group home..getting more bids
A25: 13521747 | B25: Solomon & BC Awosanya | G25: 2. APPOINTMENT | H25: Peak Leads Group | J25: 46066 | K25: Chris Cornolo | L25: 0 | M25: 16468 | N25: D - Mr. Only, Mrs was not available. Customer thought a whole bathroom would be $4/$5k.
A26: 13540362 | B26: Craig Heyrman | G26: 2. APPOINTMENT | H26: Peak Leads Group | J26: 46065 | K26: Mike Smeed | N26: Appointment Cancelled
A27: 13534946 | B27: Ramesh Singh | G27: 4. SOLD | H27: Peak Leads Group | J27: 46065 | K27: Tom Seesz | L27: 10 | M27: 22000 | N27: Sold
A28: 13518864 | B28: David & Robert Fox | G28: 2. APPOINTMENT | H28: Peak Leads Group | J28: 46064 | K28: Chris Cornolo | L28: 3 | M28: 16870 | N28: Met with Mr and his husband. Very nice home built in 2019. No major issues, but this was one of 4 projects they are considering. They were drunk, and had mad city out the day before for cabinet refacing, and absolutely hated the presentation and process. $35k for the k
A29: 13531401 | B29: Mike & Varma Hollywood | G29: 2. APPOINTMENT | H29: Peak Leads Group | J29: 46064 | K29: Tom Jaeger | N29: Cancelled
A30: 13497277 | B30: Marliyn Proulx | G30: 2. APPOINTMENT | H30: Peak Leads Group | J30: 46059 | K30: Sarah Money | L30: 2 | M30: 6500 | N30: Homeowner gave not correct address, its the house across the street, would have to get right address, just wanted shower walls nothing else, got pricing from Ken, going to sleep on it, their contractor was there the whole time listening…..they wanted onyx
A31: 13452877 | B31: Bijay & Suk Motey | C31: (612) 800-3911 | E31: moteybijay01@gmail.com | G31: 2. APPOINTMENT | H31: Peak Leads Group | I31: 46055.457 | J31: 46056 | K31: Mike Smeed | L31: 3 | M31: 17750 | N31: Said they had a bid from "KDesign" for 10K.. I highly doubt it.
A32: 13440218 | B32: Rodney Beystrom | C32: (952) 769-3011 | E32: rodneybey@mchsi.com | G32: 2. APPOINTMENT | H32: Peak Leads Group | I32: 46054.501 | J32: 46063 | K32: Tom Seesz | L32: 0 | N32: Wasn't happy that I was a half hour late due to previous appt. Had company coming back. Basement bath. When I got there he said, let's cut to the case, I have a bid for $8,000 and I told that guy that was too much money. Said he is going to do it himself if we can't beat that price.
A33: 13437357 | B33: Paul C. LaManna | C33: (651) 373-5318 | E33: paulclamanna@icloud.com | G33: 2. APPOINTMENT | H33: Peak Leads Group | I33: 46053.939 | J33: 46060 | K33: Sarah Money | L33: 2 | M33: 15054 | N33: Homeowner wanted to replace his tub shower, he was definitely on some drug and wasn't completely all there, he said he had Trident and Mad City scheduled but then tried to rebook on our calendar again, he was trying to get it done for 10k he thought that was a lot, but wanted a door and rain combo and subway tile walls
A34: 13428065 | B34: Eric Kangar | C34: (612) 239-7943 | E34: ekangar154@gmail.com | G34: 2. APPOINTMENT | H34: Peak Leads Group | I34: 46052.592 | J34: 46056 | K34: Tom Seesz | L34: 2 | M34: 29833 | N34: D. Customer was not very nice. Rude. Complete bathroom remodel when I gave them price 29,833. He told me it was way too much money. His budget was 10 to 12,000 we were the first end he's getting one more bid on Friday told me if the next bid was not in his price range he wasn't gonna do anything. There were no issues with the bathroom other than it was filthy dirty. ￼
A35: 13387630 | B35: Annette & Frederick Wilson | C35: (612) 328-6091 | E35: annette7450berkshire@yahoo.com | G35: 3. Proposal | H35: Peak Leads Group | I35: 46050.162 | J35: 46051 | K35: Tom Seesz | L35: 2 | M35: 14900 | N35: Gave them pricing. He said that his budget was $6000. Also told me we were approximately the same price as the Debella.￼
A36: 13360488 | B36: Randy & Jill Duevel | C36: (612) 965-4814 | E36: rjduevel@yahoo.com | G36: 2. APPOINTMENT | H36: Peak Leads Group | I36: 46048.82 | J36: 46052 | K36: Tom Seesz | L36: 1 | M36: 21992 | N36: when I got there, the whole bathroom has been gutted. He asked me how far out are we? I said 6 to 8 weeks. He didn't like that, but he could live with it. When I was given him my presentation and we talked about if you want to Menards and bought the product and did it himself it'd be about six to $8000. He looked at me and said while my budget is eight to $10,000 I talked to him into letting me go on gave him the price over $20,000. He did informed me that he did a bathroom four years ago and he did the whole bathroom for $20,000. All we were bidding out was a 36 x 60 shower base with glass walls 90° return panel and moving the toilet when he asked me what the toilet would cost to move it. I told him a little under $1000. He laughed at me and said it's only 30 inches that I wanna move it. I said well that's what it is. He then said I guess I'll be doing it myself. ￼

Sheet Hatch Recap
A1: Month | B1: Contacts Launched | C1: Contact Responds | D1: Response Rate | E1: Sales
A2: March | D2: =C2/B2 -> #DIV/0! | E2: 0
A3: April | D3: =C3/B3 -> #DIV/0! | E3: 0
A4: May | D4: =C4/B4 -> #DIV/0! | E4: 0
A5: June | D5: =C5/B5 -> #DIV/0! | E5: 0
A6: July | D6: =C6/B6 -> #DIV/0! | E6: 0
A7: August | D7: =C7/B7 -> #DIV/0! | E7: 0
A8: September | D8: =C8/B8 -> #DIV/0! | E8: 0
A9: October | D9: =C9/B9 -> #DIV/0! | E9: 0

Sheet Hatch responses
A1: Name | B1: Added to Campaign | C1: Response Date | D1: Sold Status | E1: Response

Sheet Bad Leads - Morgan
A1: Source | B1: Date | C1: Name | D1: Reason | E1: Refund Requested
